allms/__init__.py
allms/chains/__init__.py
allms/chains/long_text_processing_chain.py
allms/constants/__init__.py
allms/constants/azure.py
allms/constants/input_data.py
allms/constants/prompt.py
allms/constants/vertex_ai.py
allms/defaults/__init__.py
allms/defaults/azure_defaults.py
allms/defaults/general_defaults.py
allms/defaults/long_text_chain.py
allms/defaults/vertex_ai.py
allms/domain/__init__.py
allms/domain/configuration.py
allms/domain/enumerables.py
allms/domain/input_data.py
allms/domain/prompt_dto.py
allms/domain/response.py
allms/exceptions/__init__.py
allms/exceptions/validation_input_data_exceptions.py
allms/models/__init__.py
allms/models/abstract.py
allms/models/azure_base.py
allms/models/azure_llama2.py
allms/models/azure_mistral.py
allms/models/azure_openai.py
allms/models/vertexai_base.py
allms/models/vertexai_gemini.py
allms/models/vertexai_gemma.py
allms/models/vertexai_palm.py
allms/utils/__init__.py
allms/utils/io_utils.py
allms/utils/logger_utils.py
allms/utils/long_text_processing_utils.py
allms/utils/response_parsing_utils.py
allms-1.0.13.dist-info/LICENSE
allms-1.0.13.dist-info/METADATA
allms-1.0.13.dist-info/WHEEL
allms-1.0.13.dist-info/RECORD
