Metadata-Version: 2.3
Name: allms
Version: 1.0.13
Summary: 
Author: Allegro Opensource
Author-email: opensource@allegro.com
Requires-Python: >=3.9.0,<4.0
Classifier: Programming Language :: Python :: 3
Classifier: Programming Language :: Python :: 3.9
Classifier: Programming Language :: Python :: 3.10
Classifier: Programming Language :: Python :: 3.11
Classifier: Programming Language :: Python :: 3.12
Classifier: Programming Language :: Python :: 3.13
Requires-Dist: fsspec (>=2025.3.0,<2026.0.0)
Requires-Dist: google-cloud-aiplatform (==1.85.0)
Requires-Dist: langchain (==0.3.21)
Requires-Dist: langchain-community (>=0.3.20,<0.4.0)
Requires-Dist: langchain-google-vertexai (>=2.0.15,<3.0.0)
Requires-Dist: langchain-openai (>=0.3.9,<0.4.0)
Requires-Dist: openai (==1.68.0)
Requires-Dist: pydantic (>=2.10.6,<3.0.0)
Requires-Dist: pydash (>=8.0.5,<9.0.0)
Requires-Dist: pytest-mock (>=3.14.0,<4.0.0)
Requires-Dist: respx (>=0.22.0,<0.23.0)
Requires-Dist: sentencepiece (>=0.2.0,<0.3.0)
Requires-Dist: tiktoken (>=0.9.0,<0.10.0)
Requires-Dist: transformers (>=4.49.0,<5.0.0)
